README.md
setup.py
py_wtf.egg-info/PKG-INFO
py_wtf.egg-info/SOURCES.txt
py_wtf.egg-info/dependency_links.txt
py_wtf.egg-info/entry_points.txt
py_wtf.egg-info/not-zip-safe
py_wtf.egg-info/top_level.txt
pywtf/__init__.py
pywtf/config.py
pywtf/main.py
pywtf/utils.py
test/testfile_comment.py
test/testfile_docstring.py
test/testfile_empty.py
test/testfile_perfect.py