Metadata-Version: 1.2
Name: py-wtf
Version: 0.0.5
Summary: A static analyzer of Python which forces you to write comments, and write them in a well-mannered way.
Home-page: https://github.com/zhoudaxia233/py-wtf
Author: Zheng Zhou
Author-email: yootaoo@gmail.com
License: MIT
Keywords: static-analyzer
Platform: UNKNOWN
Requires-Python: >=3.5
